system_maintenance/__init__.py
system_maintenance/admin.py
system_maintenance/app_settings.py
system_maintenance/apps.py
system_maintenance/models.py
system_maintenance/urls.py
system_maintenance/views.py
system_maintenance/migrations/0001_initial.py
system_maintenance/migrations/0002_auto_20181214_2122.py
system_maintenance/migrations/__init__.py
system_maintenance/static/system_maintenance/css/app.css
system_maintenance/static/system_maintenance/js/app.js
system_maintenance/templates/system_maintenance/_documentation_record_list_item.html
system_maintenance/templates/system_maintenance/_maintenance_record_list_item.html
system_maintenance/templates/system_maintenance/_pagination.html
system_maintenance/templates/system_maintenance/_panel.html
system_maintenance/templates/system_maintenance/_related_records_button.html
system_maintenance/templates/system_maintenance/_summary_button.html
system_maintenance/templates/system_maintenance/authentication.html
system_maintenance/templates/system_maintenance/base.html
system_maintenance/templates/system_maintenance/documentation_record_detail.html
system_maintenance/templates/system_maintenance/documentation_record_list.html
system_maintenance/templates/system_maintenance/maintenance_record_detail.html
system_maintenance/templates/system_maintenance/maintenance_record_list.html
system_maintenance/templates/system_maintenance/raw.html
system_maintenance/templates/system_maintenance/system_maintenance_home.html
system_maintenance/tests/__init__.py
system_maintenance/tests/utilities.py
system_maintenance/tests/functional/__init__.py
system_maintenance/tests/functional/base.py
system_maintenance/tests/functional/test_authentication.py
system_maintenance/tests/functional/test_layout_and_styling.py
system_maintenance/tests/unit/__init__.py
system_maintenance/tests/unit/test_models.py
system_maintenance/tests/unit/test_views.py
system_maintenance/tests/unit/tests.py
django_system_maintenance-0.4.6.dist-info/LICENSE
django_system_maintenance-0.4.6.dist-info/METADATA
django_system_maintenance-0.4.6.dist-info/WHEEL
django_system_maintenance-0.4.6.dist-info/top_level.txt
django_system_maintenance-0.4.6.dist-info/RECORD
