Metadata-Version: 2.1
Name: django-system-maintenance
Version: 0.4.6
Summary: A Django app to document and track the administration and maintenance of computer systems
Home-page: https://github.com/mfcovington/django-system-maintenance
Author: Michael F. Covington
Author-email: mfcovington@gmail.com
License: BSD License
Keywords: sysadmin system administration documentation maintenance
Platform: UNKNOWN
Classifier: Development Status :: 3 - Alpha
Classifier: Environment :: Web Environment
Classifier: Framework :: Django
Classifier: Framework :: Django :: 2.0
Classifier: Framework :: Django :: 2.1
Classifier: Intended Audience :: Developers
Classifier: Intended Audience :: Information Technology
Classifier: Intended Audience :: System Administrators
Classifier: License :: OSI Approved :: BSD License
Classifier: Operating System :: OS Independent
Classifier: Programming Language :: Python
Classifier: Programming Language :: Python :: 3
Classifier: Programming Language :: Python :: 3.4
Classifier: Programming Language :: Python :: 3.5
Classifier: Programming Language :: Python :: 3.6
Classifier: Programming Language :: Python :: 3.7
Classifier: Programming Language :: Python :: 3 :: Only
Classifier: Topic :: Documentation
Classifier: Topic :: Internet :: WWW/HTTP
Classifier: Topic :: Internet :: WWW/HTTP :: Dynamic Content
Classifier: Topic :: System :: Systems Administration
Requires-Dist: Django (<3.0,>=2.0)
Requires-Dist: django-markupfield-helpers (>=0.1.1)
Requires-Dist: django-project-home-templatetags (>=0.1.0)
